what2do/__init__.py
what2do/__main__.py
what2do/cli.py
what2do/core.py
what2do/git_history.py
what2do/what2do
what2do-0.1.3.dist-info/METADATA
what2do-0.1.3.dist-info/WHEEL
what2do-0.1.3.dist-info/entry_points.txt
what2do-0.1.3.dist-info/licenses/LICENSE
what2do-0.1.3.dist-info/RECORD
