Metadata-Version: 2.4
Name: what2do
Version: 0.1.3
Summary: Find TODO comments in code files
Project-URL: Homepage, https://github.com/urineri/what2do
Project-URL: Repository, https://github.com/urineri/what2do
Project-URL: Issues, https://github.com/urineri/what2do/issues
Author-email: Uri Neri <uri.neri@gmail.com>
License-Expression: MIT
License-File: LICENSE
Keywords: analysis,code,comments,development,todo
Classifier: Development Status :: 4 - Beta
Classifier: Intended Audience :: Developers
Classifier: License :: OSI Approved :: MIT License
Classifier: Operating System :: OS Independent
Classifier: Programming Language :: Python :: 3
Classifier: Programming Language :: Python :: 3.8
Classifier: Programming Language :: Python :: 3.9
Classifier: Programming Language :: Python :: 3.10
Classifier: Programming Language :: Python :: 3.11
Classifier: Programming Language :: Python :: 3.12
Classifier: Topic :: Software Development :: Libraries :: Python Modules
Classifier: Topic :: Software Development :: Quality Assurance
Classifier: Topic :: Utilities
Requires-Python: >=3.8
